faissqlite/__init__.py
faissqlite/api.py
faissqlite/cli.py
faissqlite/config.py
faissqlite/db.py
faissqlite/plugins.py
faissqlite/utils.py
faissqlite/vector_store.py
faissqlite-0.1.0.dist-info/licenses/LICENSE
faissqlite-0.1.0.dist-info/METADATA
faissqlite-0.1.0.dist-info/WHEEL
faissqlite-0.1.0.dist-info/entry_points.txt
faissqlite-0.1.0.dist-info/top_level.txt
faissqlite-0.1.0.dist-info/RECORD
