Metadata-Version: 2.4
Name: faissqlite
Version: 0.1.0
Summary: Persistent and efficient vector store using FAISS + SQLite
Home-page: https://github.com/praveencs87/faissqlite
Author: Your Name
Author-email: your.email@example.com
License: MIT
Classifier: Programming Language :: Python :: 3
Classifier: License :: OSI Approved :: MIT License
Classifier: Operating System :: OS Independent
Requires-Python: >=3.7
License-File: LICENSE
Requires-Dist: faiss-cpu>=1.7.4
Requires-Dist: numpy>=1.21.0
Provides-Extra: api
Requires-Dist: fastapi>=0.100.0; extra == "api"
Dynamic: author
Dynamic: author-email
Dynamic: classifier
Dynamic: home-page
Dynamic: license
Dynamic: license-file
Dynamic: provides-extra
Dynamic: requires-dist
Dynamic: requires-python
Dynamic: summary
